gmdkit/__init__.py
gmdkit/casting/__init__.py
gmdkit/casting/color.py
gmdkit/casting/id_rules.py
gmdkit/casting/level_props.py
gmdkit/casting/object_props.py
gmdkit/constants/__init__.py
gmdkit/constants/game/__init__.py
gmdkit/constants/game/guideline/__init__.py
gmdkit/constants/game/speed/__init__.py
gmdkit/constants/paths/__init__.py
gmdkit/defaults/__init__.py
gmdkit/defaults/color_default.py
gmdkit/defaults/level.py
gmdkit/defaults/objects.py
gmdkit/extra/globed.py
gmdkit/extra/text.py
gmdkit/functions/__init__.py
gmdkit/functions/color.py
gmdkit/functions/merging.py
gmdkit/functions/misc.py
gmdkit/functions/object.py
gmdkit/functions/object_list.py
gmdkit/functions/remapping.py
gmdkit/mappings/__init__.py
gmdkit/mappings/color_id/__init__.py
gmdkit/mappings/color_prop/__init__.py
gmdkit/mappings/lvl_prop/__init__.py
gmdkit/mappings/lvl_prop/level/__init__.py
gmdkit/mappings/lvl_prop/level/editor/__init__.py
gmdkit/mappings/lvl_prop/level/official/__init__.py
gmdkit/mappings/lvl_prop/list/__init__.py
gmdkit/mappings/obj_enum/__init__.py
gmdkit/mappings/obj_enum/easing/__init__.py
gmdkit/mappings/obj_enum/item_label/__init__.py
gmdkit/mappings/obj_enum/item_label/alignment/__init__.py
gmdkit/mappings/obj_enum/item_label/special_id/__init__.py
gmdkit/mappings/obj_enum/level/__init__.py
gmdkit/mappings/obj_enum/level/color_1_7/__init__.py
gmdkit/mappings/obj_enum/level/color_1_7/player_color/__init__.py
gmdkit/mappings/obj_enum/old_color/__init__.py
gmdkit/mappings/obj_enum/single_color_type/__init__.py
gmdkit/mappings/obj_enum/trigger/__init__.py
gmdkit/mappings/obj_enum/trigger/adv_follow/__init__.py
gmdkit/mappings/obj_enum/trigger/adv_follow/init/__init__.py
gmdkit/mappings/obj_enum/trigger/adv_follow/mode/__init__.py
gmdkit/mappings/obj_enum/trigger/arrow/__init__.py
gmdkit/mappings/obj_enum/trigger/arrow/direction/__init__.py
gmdkit/mappings/obj_enum/trigger/bpm/__init__.py
gmdkit/mappings/obj_enum/trigger/bpm/speed/__init__.py
gmdkit-0.4.0.dist-info/licenses/LICENSE
gmdkit-0.4.0.dist-info/METADATA
gmdkit-0.4.0.dist-info/WHEEL
gmdkit-0.4.0.dist-info/top_level.txt
gmdkit-0.4.0.dist-info/RECORD
