Metadata-Version: 2.4
Name: gmdkit
Version: 0.4.0
Summary: A toolkit for handling Geometry Dash level data.
Author: HDanke
License: MIT
Keywords: geometry-dash,gmd,levels,parser,editor
Classifier: Development Status :: 3 - Alpha
Classifier: Intended Audience :: Developers
Classifier: License :: OSI Approved :: MIT License
Classifier: Programming Language :: Python :: 3
Classifier: Programming Language :: Python :: 3.9
Classifier: Programming Language :: Python :: 3.10
Classifier: Programming Language :: Python :: 3.11
Requires-Python: >=3.9
License-File: LICENSE
Requires-Dist: zstandard
Requires-Dist: websocket-client
Dynamic: license-file
